PiMath/__init__.py
PiMath/colors.py
PiMath/example.py
PiMath/geometry.py
PiMath/number.py
PiMath/primes.py
PiMath/roman.py
pimath-0.8.0.dist-info/licenses/LICENSE
pimath-0.8.0.dist-info/METADATA
pimath-0.8.0.dist-info/WHEEL
pimath-0.8.0.dist-info/top_level.txt
pimath-0.8.0.dist-info/RECORD
