Metadata-Version: 2.4
Name: PiMath
Version: 0.8.0
Summary: A math library
Author-email: Álvaro Perseo <ayuskyap@gmail.com>
License: MIT License
Project-URL: Homepage, https://github.com/Pygramer78/PiMath
Keywords: math,geometry,numbers
Classifier: License :: OSI Approved :: MIT License
Classifier: Operating System :: OS Independent
Classifier: Programming Language :: Python :: 3
Classifier: Topic :: Scientific/Engineering :: Mathematics
Requires-Python: >=3.9
License-File: LICENSE
Requires-Dist: matplotlib
Dynamic: license-file
